appm/__init__.py
appm/__version__.py
appm/default.py
appm/exceptions.py
appm/manager.py
appm/model.py
appm/py.typed
appm/utils.py
appm-0.2.0.dist-info/WHEEL
appm-0.2.0.dist-info/METADATA
appm-0.2.0.dist-info/RECORD
