Metadata-Version: 2.3
Name: appm
Version: 0.2.0
Summary: APPN Phenomate Project Manager
Requires-Dist: pydantic>=2.11.7
Requires-Dist: ruamel-yaml>=0.18.14
Requires-Dist: sphinx ; extra == 'docs'
Requires-Python: >=3.11
Provides-Extra: docs
